{"arch": "amd64", "os": "linux", "functions": [{"address": 4195440, "return_address": {"memory": {"register": "RSP", "offset": 0}, "type": "L"}, "return_stack_pointer": {"register": "RSP", "offset": 8, "type": "L"}, "parameters": [{"register": "RDI", "type": "*b"}], "return_values": [{"register": "RAX", "type": "i"}], "is_variadic": true}, {"address": 4195744, "return_address": {"memory": {"register": "RSP", "offset": 0}, "type": "L"}, "return_stack_pointer": {"register": "RSP", "offset": 8, "type": "L"}, "return_values": [{"register": "RAX", "type": "l"}]}, {"address": 4195424, "return_address": {"memory": {"register": "RSP", "offset": 0}, "type": "L"}, "return_stack_pointer": {"register": "RSP", "offset": 8, "type": "L"}, "parameters": [{"register": "RDI", "type": "i"}], "return_values": [{"register": "RAX", "type": "i"}]}], "variables": [], "symbols": [[4195440, "printf"], [4195744, "brake_off"], [4195424, "putchar"]], "memory": [{"address": 4195424, "is_writeable": false, "is_executable": true, "data": "ff25b20b2000"}, {"address": 4195440, "is_writeable": false, "is_executable": true, "data": "ff25aa0b2000"}, {"address": 4195744, "is_writeable": false, "is_executable": true, "data": "50bfa4074000beb707400031c0e8befeffffbf0a000000e8a4feffff58c3"}], "stack": {"address": 87960931794944, "size": 24576, "start_offset": 4096}}